{
  "clientes": [
    {
      "id": "1",
      "avatarURL": "https://img.freepik.com/free-psd/3dillustration-person-with-sunglasses_23-2149436188.jpg?size=626&ext=jpg",
      "name": "Danny G.",
      "city": "Quito",
      "country": "Ecuador",
      "address": "Ladrón de Guevara E11-253",
      "age": 38
    },
    {
      "id": "2",
      "avatarURL": "https://img.freepik.com/free-psd/3dillustration-person-with-sunglasses_23-2149436188.jpg?size=626&ext=jpg",
      "name": "Cristina",
      "city": "Quito",
      "country": "Ecuador",
      "address": "Av. Colón y 10 de Agosto",
      "age": 15
    },
    {
      "id": "3",
      "avatarURL": "https://img.freepik.com/free-psd/3dillustration-person-with-sunglasses_23-2149436188.jpg?size=626&ext=jpg",
      "name": "Jorge",
      "city": "Ambato",
      "country": "Ecuador",
      "address": "La República y 5 de Septiembre",
      "age": 25
    },
    {
      "id": "4",
      "avatarURL": "https://img.freepik.com/free-psd/3dillustration-person-with-sunglasses_23-2149436188.jpg?size=626&ext=jpg",
      "name": "Santiago",
      "city": "Guayaquil",
      "country": "Ecuador",
      "address": "10 de Agosto",
      "age": 18,
      "edad": null
    }
  ]
}